ec2_connect_manager-0.1.0.dist-info/licenses/LICENSE
ec2manager/__init__.py
ec2manager/cli.py
ec2manager/manager.py
ec2_connect_manager-0.1.0.dist-info/METADATA
ec2_connect_manager-0.1.0.dist-info/WHEEL
ec2_connect_manager-0.1.0.dist-info/entry_points.txt
ec2_connect_manager-0.1.0.dist-info/top_level.txt
ec2_connect_manager-0.1.0.dist-info/RECORD
